distributed_a2a/__init__.py
distributed_a2a/agent.py
distributed_a2a/client.py
distributed_a2a/executors.py
distributed_a2a/model.py
distributed_a2a/registry.py
distributed_a2a/server.py
distributed_a2a-0.1.4.dist-info/licenses/LICENSE
distributed_a2a-0.1.4.dist-info/METADATA
distributed_a2a-0.1.4.dist-info/WHEEL
distributed_a2a-0.1.4.dist-info/top_level.txt
distributed_a2a-0.1.4.dist-info/RECORD
