Metadata-Version: 2.4
Name: distributed_a2a
Version: 0.1.4
Summary: A library for building A2A agents with routing capabilities
Home-page: https://github.com/Barra-Technologies/distributed-a2a
Author: Fabian Bell
Author-email: Fabian Bell <fabian.bell@barrabytes.com>
License: MIT
Project-URL: Homepage, https://github.com/Barra-Technologies/distributed-a2a
Project-URL: Repository, https://github.com/Barra-Technologies/distributed-a2a
Classifier: Development Status :: 3 - Alpha
Classifier: Intended Audience :: Developers
Classifier: Topic :: Software Development :: Libraries :: Python Modules
Classifier: License :: OSI Approved :: MIT License
Classifier: Programming Language :: Python :: 3
Classifier: Programming Language :: Python :: 3.10
Classifier: Programming Language :: Python :: 3.11
Classifier: Programming Language :: Python :: 3.12
Requires-Python: >=3.10
License-File: LICENSE
Requires-Dist: langchain>=0.1.0
Requires-Dist: langchain-core>=0.1.0
Requires-Dist: langchain-openai>=0.0.5
Requires-Dist: langgraph>=0.0.20
Requires-Dist: pydantic>=2.0.0
Requires-Dist: boto3>=1.28.0
Requires-Dist: a2a>=0.1.0
Dynamic: author
Dynamic: home-page
Dynamic: license-file
Dynamic: requires-python
